{
    "_id": "BW3fGYdirVHuN61r",
    "img": "icons/equipment/head/mask-carved-wood-brown.webp",
    "name": "Amaranthine Visage",
    "system": {
        "baseItem": null,
        "bulk": {
            "value": 0.1
        },
        "containerId": null,
        "description": {
            "value": "<p>The shape of this 2-foot-tall wooden mask, worn by the secretive leaders of the elves who inhabit the Mordant Spire, mirrors the tower itself. While wearing it, your innards turn to purple smoke, giving you resistance 10 to precision damage.</p>\n<p><strong>Activate—Eternal Renewal</strong> <span class=\"action-glyph\">r</span> (healing)</p>\n<p><strong>Frequency</strong> once per day</p>\n<p><strong>Trigger</strong> Your dying condition would reach the value that would cause you to die</p><hr /><p><strong>Effect</strong> You Sublimate Self. You lose the dying condition, gaining or increasing your wounded condition as normal, and gain fast healing 20 for 1 minute. You can use Eternal Renewal even while @UUID[Compendium.pf2e.conditionitems.Item.Unconscious] or otherwise unable to act.</p>\n<p><strong>Activate—Sublimate Self</strong> <span class=\"action-glyph\">2</span> (air, concentrate, polymorph) Your body transforms completely into purple vapor for 5 minutes, with the effects of vapor form.</p>"
        },
        "hardness": 0,
        "hp": {
            "max": 0,
            "value": 0
        },
        "level": {
            "value": 17
        },
        "material": {
            "grade": null,
            "type": null
        },
        "price": {
            "value": {
                "gp": 15000
            }
        },
        "publication": {
            "license": "ORC",
            "remaster": true,
            "title": "Pathfinder Lost Omens High Seas"
        },
        "quantity": 1,
        "rules": [],
        "size": "med",
        "traits": {
            "rarity": "rare",
            "value": [
                "invested",
                "magical"
            ]
        },
        "usage": {
            "value": "wornmask"
        }
    },
    "type": "equipment"
}
