{
    "_id": "WtswAs4isNAQUNey",
    "folder": "Spw45hxABNcRd0BT",
    "img": "icons/sundries/books/book-red-exclamation.webp",
    "name": "Inked Cache",
    "system": {
        "actionType": {
            "value": "passive"
        },
        "actions": {
            "value": null
        },
        "category": "class",
        "description": {
            "value": "<p>You've learned to use your Twilight Talon's mark to secret away contraband. The tattoo's level increases to 10, unless it was already higher, and it gains the abilities of a greater retrieval belt. As a part of activating the tattoo to Store Item, you can attempt a @Check[deception|against:perception] check against the Perception DCs of all creatures that are currently observing you. On a success, a creature doesn't notice you use Store Item.</p>"
        },
        "level": {
            "value": 10
        },
        "prerequisites": {
            "value": [
                {
                    "value": "Talon’s Mark"
                }
            ]
        },
        "publication": {
            "license": "ORC",
            "remaster": true,
            "title": "Pathfinder Lost Omens Hellfire Dispatches"
        },
        "rules": [],
        "subfeatures": {
            "proficiencies": {},
            "senses": {},
            "suppressedFeatures": []
        },
        "traits": {
            "rarity": "common",
            "value": [
                "archetype"
            ]
        }
    },
    "type": "feat"
}
